face_enhancement_service/__init__.py
face_enhancement_service/_version.py
face_enhancement_service/config.py
face_enhancement_service/face_enhancer_api.py
face_enhancement_service/face_enhancer_client.py
face_enhancement_service/__pycache__/__init__.cpython-310.pyc
face_enhancement_service/__pycache__/config.cpython-310.pyc
face_enhancement_service/__pycache__/face_enhancer_api.cpython-310.pyc
face_enhancement_service/__pycache__/face_enhancer_client.cpython-310.pyc
face_enhancement_service-1.0.1.dist-info/licenses/LICENSE
face_enhancement_service-1.0.1.dist-info/METADATA
face_enhancement_service-1.0.1.dist-info/WHEEL
face_enhancement_service-1.0.1.dist-info/entry_points.txt
face_enhancement_service-1.0.1.dist-info/top_level.txt
face_enhancement_service-1.0.1.dist-info/RECORD
