Metadata-Version: 2.4
Name: face-enhancement-service
Version: 1.0.1
Summary: High-performance REST API for real-time face enhancement
Home-page: https://github.com/livlyv/face-enhancement-service
Author: Face Enhancement Team
Author-email: Face Enhancement Team <info@livlyv.com>
Maintainer-email: Face Enhancement Team <info@livlyv.com>
License: MIT
Project-URL: Homepage, https://github.com/livlyv/face-enhancement-service
Project-URL: Documentation, https://github.com/livlyv/face-enhancement-service#readme
Project-URL: Repository, https://github.com/livlyv/face-enhancement-service.git
Project-URL: Bug Tracker, https://github.com/livlyv/face-enhancement-service/issues
Keywords: face-enhancement,rest-api,fastapi,computer-vision,opencv,mediapipe,beauty-filter,skin-smoothing,real-time
Classifier: Development Status :: 5 - Production/Stable
Classifier: Intended Audience :: Developers
Classifier: License :: OSI Approved :: MIT License
Classifier: Operating System :: OS Independent
Classifier: Programming Language :: Python :: 3
Classifier: Programming Language :: Python :: 3.8
Classifier: Programming Language :: Python :: 3.9
Classifier: Programming Language :: Python :: 3.10
Classifier: Programming Language :: Python :: 3.11
Classifier: Topic :: Software Development :: Libraries :: Python Modules
Classifier: Topic :: Multimedia :: Graphics :: Graphics Conversion
Classifier: Topic :: Scientific/Engineering :: Image Processing
Requires-Python: >=3.8
License-File: LICENSE
Requires-Dist: fastapi>=0.104.1
Requires-Dist: uvicorn[standard]>=0.24.0
Requires-Dist: opencv-python>=4.8.1.78
Requires-Dist: numpy>=1.24.3
Requires-Dist: scipy>=1.11.3
Requires-Dist: Pillow>=10.0.1
Requires-Dist: imutils>=0.5.4
Requires-Dist: scikit-image>=0.21.0
Requires-Dist: mediapipe>=0.10.7
Requires-Dist: python-jose[cryptography]>=3.3.0
Requires-Dist: passlib[bcrypt]>=1.7.4
Requires-Dist: python-multipart>=0.0.6
Requires-Dist: pydantic>=2.5.0
Requires-Dist: structlog>=23.2.0
Requires-Dist: gunicorn>=21.2.0
Requires-Dist: python-dotenv>=1.0.0
Provides-Extra: dev
Requires-Dist: pytest>=7.0.0; extra == "dev"
Requires-Dist: pytest-asyncio>=0.21.0; extra == "dev"
Requires-Dist: black>=22.0.0; extra == "dev"
Requires-Dist: flake8>=4.0.0; extra == "dev"
Provides-Extra: linux
Requires-Dist: uvloop>=0.19.0; extra == "linux"
Requires-Dist: httptools>=0.6.1; extra == "linux"
Dynamic: author
Dynamic: home-page
Dynamic: license-file
Dynamic: requires-python
